{
"StructuralAnalysisModel": {
	"BIM": "unknown",
	"description": "",
	"engineer": "",
	"units": {
		"force": "",
		"length": "",
		"time": "",
		"temperature": ""
	},
	"properties": {
		"uniaxialMaterials": [
			{"name": "1", "type": "Concrete04", "Ec": 2.93e+07, "fc": -32800, "epsc": -0.002, "ft": 0, "epstu": 0, "epscu": -0.0033, "beta": 0.1},
			{"name": "2", "type": "Concrete04", "Ec": 2.93e+07, "fc": -35682.8, "epsc": -0.00287891, "ft": 0, "epstu": 0, "epscu": -0.00901048, "beta": 0.1},
			{"name": "3", "type": "Steel02", "E": 1.9e+08, "fy": 526200, "b": 0.01, "R0": 18, "cR1": 0.925, "cR2": 0.15, "a1": 0, "a2": 1, "a3": 0, "a4": 1, "sigini": 0},
			{"name": "4", "type": "MinMaxMaterial", "material": "3", "epsMin": -1e+16, "epsMax": 0.1},
			{"name": "5", "type": "Concrete04", "Ec": 2.93e+07, "fc": -25000, "epsc": -0.002, "ft": 0, "epstu": 0, "epscu": -0.0033, "beta": 0.1},
			{"name": "6", "type": "Concrete04", "Ec": 2.93e+07, "fc": -29639.3, "epsc": -0.0038557, "ft": 0, "epstu": 0, "epscu": -0.0117943, "beta": 0.1},
			{"name": "7", "type": "Steel02", "E": 1.9e+08, "fy": 400000, "b": 0.01, "R0": 18, "cR1": 0.925, "cR2": 0.15, "a1": 0, "a2": 1, "a3": 0, "a4": 1, "sigini": 0},
			{"name": "8", "type": "MinMaxMaterial", "material": "7", "epsMin": -1e+16, "epsMax": 0.1},
			{"name": "10", "type": "Steel02", "E": 2.06e+08, "fy": 1.86e+06, "b": 0.01, "R0": 18, "cR1": 0.925, "cR2": 0.15, "a1": 0, "a2": 1, "a3": 0, "a4": 1, "sigini": 1.03881e+06},
			{"name": "4001", "type": "Steel02", "E": 1.767e+08, "fy": 309570, "b": 0.01, "R0": 18, "cR1": 0.925, "cR2": 0.15, "a1": 0, "a2": 1, "a3": 0, "a4": 1, "sigini": 0},
			{"name": "4002", "type": "ElasticMaterial", "Epos": 10000, "Eneg": 10000, "eta": 0},
			{"name": "4003", "type": "ElasticMaterial", "Epos": 1e+08, "Eneg": 1e+08, "eta": 0},
			{"name": "4004", "type": "ElasticMaterial", "Epos": 0.01, "Eneg": 0.01, "eta": 0},
			{"name": "4011", "type": "EPPGap", "E": 18000, "eta": 0, "fy": 1e+08, "gap": 0.0001, "damageFlag": 0},
			{"name": "4012", "type": "EPPGap", "E": 10000, "eta": 0, "fy": -1e+08, "gap": -0.0001, "damageFlag": 0},
			{"name": "4013", "type": "EPPGap", "E": 1.767e+08, "eta": 0, "fy": 1e+08, "gap": 0.02, "damageFlag": 0},
			{"name": "4014", "type": "EPPGap", "E": 10000, "eta": 0, "fy": -1e+08, "gap": -0.02, "damageFlag": 0},
			{"name": "4015", "type": "ParallelMaterial", "materials": ["4011", "4012", "4013", "4014"]}
		],
		"ndMaterials": [

		],
		"sections": [
			{"name": "100", "type": "FiberSection3d", "torsion": 161492, "fibers": [
				{"coord": [-0.261667, 0.239792], "area": 0.0003125, "material": "1"},
				{"coord": [-0.110625, -0.261667], "area": 0.0003125, "material": "1"},
				{"coord": [0.239792, 0.261667], "area": 0.0003125, "material": "1"},
				{"coord": [-0.268333, -0.256875], "area": 0.00034375, "material": "1"},
				{"coord": [-0.239792, -0.261667], "area": 0.0003125, "material": "1"},
				{"coord": [0.268333, -0.089375], "area": 0.00034375, "material": "1"},
				{"coord": [0.256875, -0.268333], "area": 0.00034375, "material": "1"},
				{"coord": [-0.256875, 0.268333], "area": 0.00034375, "material": "1"},
				{"coord": [0.268333, 0.256875], "area": 0.00034375, "material": "1"},
				{"coord": [0.110208, 0.261667], "area": 0.000325, "material": "1"},
				{"coord": [-0.261667, 0.109792], "area": 0.0003375, "material": "1"},
				{"coord": [0.261667, -0.239792], "area": 0.0003125, "material": "1"},
				{"coord": [0.123542, -0.268333], "area": 0.00034375, "material": "1"},
				{"coord": [0.041875, -0.261667], "area": 0.0003375, "material": "1"},
				{"coord": [-0.190208, -0.268333], "area": 0.00034375, "material": "1"},
				{"coord": [0.261667, 0.0575], "area": 0.0003125, "material": "1"},
				{"coord": [0.268333, -0.190208], "area": 0.00034375, "material": "1"},
				{"coord": [-0.0560417, 0.268333], "area": 0.00034375, "material": "1"},
				{"coord": [0.190208, 0.268333], "area": 0.00034375, "material": "1"},
				{"coord": [-0.268333, -0.0464583], "area": 0.00034375, "material": "1"},
				{"coord": [-0.268333, 0.190208], "area": 0.00034375, "material": "1"},
				{"coord": [-0.121354, 0.261667], "area": 0.0001625, "material": "1"},
				{"coord": [-0.261667, -0.121562], "area": 0.00015625, "material": "1"},
				{"coord": [0.142917, -0.261667], "area": 0.0003125, "material": "1"},
				{"coord": [-0.223542, -0.268333], "area": 0.00034375, "material": "1"},
				{"coord": [0.268333, 0.0902083], "area": 0.00034375, "material": "1"},
				{"coord": [0.0560417, 0.268333], "area": 0.00034375, "material": "1"},
				{"coord": [-0.175208, 0.261667], "area": 0.0003125, "material": "1"},
				{"coord": [-0.261667, 0.041875], "area": 0.0003375, "material": "1"},
				{"coord": [-0.261667, -0.175208], "area": 0.0003125, "material": "1"},
				{"coord": [0.261667, 0.175208], "area": 0.0003125, "material": "1"},
				{"coord": [0.175208, -0.261667], "area": 0.0003125, "material": "1"},
				{"coord": [-0.0252083, -0.261667], "area": 0.0003125, "material": "1"},
				{"coord": [0.261667, 0.142917], "area": 0.0003125, "material": "1"},
				{"coord": [0.268333, -0.223542], "area": 0.00034375, "material": "1"},
				{"coord": [-0.142917, 0.261667], "area": 0.0003125, "material": "1"},
				{"coord": [0.223542, 0.268333], "area": 0.00034375, "material": "1"},
				{"coord": [-0.261667, -0.142917], "area": 0.0003125, "material": "1"},
				{"coord": [-0.268333, 0.223542], "area": 0.00034375, "material": "1"},
				{"coord": [0.261667, -0.00791667], "area": 0.0003375, "material": "1"},
				{"coord": [0.2075, -0.261667], "area": 0.0003125, "material": "1"},
				{"coord": [-0.156875, -0.268333], "area": 0.00034375, "material": "1"},
				{"coord": [0.261667, 0.2075], "area": 0.0003125, "material": "1"},
				{"coord": [-0.2075, 0.261667], "area": 0.0003125, "material": "1"},
				{"coord": [0.156875, 0.268333], "area": 0.00034375, "material": "1"},
				{"coord": [-0.261667, -0.2075], "area": 0.0003125, "material": "1"},
				{"coord": [-0.268333, 0.156875], "area": 0.00034375, "material": "1"},
				{"coord": [0.268333, -0.156875], "area": 0.00034375, "material": "1"},
				{"coord": [-0.0783333, -0.261667], "area": 0.0003125, "material": "1"},
				{"coord": [-0.0575, -0.261667], "area": 0.0003125, "material": "1"},
				{"coord": [0.261667, -0.041875], "area": 0.0003375, "material": "1"},
				{"coord": [0.268333, -0.123542], "area": 0.00034375, "material": "1"},
				{"coord": [0.0770833, 0.261667], "area": 0.000325, "material": "1"},
				{"coord": [0.0222917, 0.268333], "area": 0.00034375, "material": "1"},
				{"coord": [-0.261667, 0.0758333], "area": 0.0003375, "material": "1"},
				{"coord": [-0.261667, 0.00791667], "area": 0.0003375, "material": "1"},
				{"coord": [0.00791667, -0.261667], "area": 0.0003375, "material": "1"},
				{"coord": [0.089375, -0.268333], "area": 0.00034375, "material": "1"},
				{"coord": [-0.142917, -0.261667], "area": 0.0003125, "material": "1"},
				{"coord": [0.261667, 0.121563], "area": 0.00015625, "material": "1"},
				{"coord": [0.261667, 0.0252083], "area": 0.0003125, "material": "1"},
				{"coord": [0.261667, -0.142917], "area": 0.0003125, "material": "1"},
				{"coord": [-0.0222917, 0.268333], "area": 0.00034375, "material": "1"},
				{"coord": [-0.0897917, 0.268333], "area": 0.00034375, "material": "1"},
				{"coord": [0.142917, 0.261667], "area": 0.0003125, "material": "1"},
				{"coord": [-0.268333, -0.013125], "area": 0.00034375, "material": "1"},
				{"coord": [-0.268333, -0.0902083], "area": 0.00034375, "material": "1"},
				{"coord": [-0.261667, 0.142917], "area": 0.0003125, "material": "1"},
				{"coord": [0.190208, -0.268333], "area": 0.00034375, "material": "1"},
				{"coord": [0.268333, 0.190208], "area": 0.00034375, "material": "1"},
				{"coord": [-0.190208, 0.268333], "area": 0.00034375, "material": "1"},
				{"coord": [-0.268333, -0.190208], "area": 0.00034375, "material": "1"},
				{"coord": [-0.013125, -0.268333], "area": 0.00034375, "material": "1"},
				{"coord": [-0.0464583, -0.268333], "area": 0.00034375, "material": "1"},
				{"coord": [-0.123542, -0.268333], "area": 0.00034375, "material": "1"},
				{"coord": [0.268333, -0.0552083], "area": 0.00034375, "material": "1"},
				{"coord": [0.268333, -0.0210417], "area": 0.00034375, "material": "1"},
				{"coord": [0.261667, -0.0758333], "area": 0.0003375, "material": "1"},
				{"coord": [0.123542, 0.268333], "area": 0.00034375, "material": "1"},
				{"coord": [0.0108333, 0.261667], "area": 0.000325, "material": "1"},
				{"coord": [0.0439583, 0.261667], "area": 0.000325, "material": "1"},
				{"coord": [-0.268333, 0.123542], "area": 0.00034375, "material": "1"},
				{"coord": [0.0758333, -0.261667], "area": 0.0003375, "material": "1"},
				{"coord": [-0.268333, 0.0552083], "area": 0.00034375, "material": "1"},
				{"coord": [0.0552083, -0.268333], "area": 0.00034375, "material": "1"},
				{"coord": [0.0210417, -0.268333], "area": 0.00034375, "material": "1"},
				{"coord": [0.261667, 0.0783333], "area": 0.0003125, "material": "1"},
				{"coord": [0.268333, 0.013125], "area": 0.00034375, "material": "1"},
				{"coord": [0.268333, 0.0464583], "area": 0.00034375, "material": "1"},
				{"coord": [-0.0770833, 0.261667], "area": 0.000325, "material": "1"},
				{"coord": [-0.0108333, 0.261667], "area": 0.000325, "material": "1"},
				{"coord": [-0.0439583, 0.261667], "area": 0.000325, "material": "1"},
				{"coord": [-0.261667, -0.0783333], "area": 0.0003125, "material": "1"},
				{"coord": [-0.261667, -0.0575], "area": 0.0003125, "material": "1"},
				{"coord": [-0.261667, -0.0252083], "area": 0.0003125, "material": "1"},
				{"coord": [-0.0902083, -0.268333], "area": 0.00034375, "material": "1"},
				{"coord": [0.0897917, 0.268333], "area": 0.00034375, "material": "1"},
				{"coord": [0.261667, -0.109792], "area": 0.0003375, "material": "1"},
				{"coord": [-0.268333, 0.089375], "area": 0.00034375, "material": "1"},
				{"coord": [-0.268333, 0.0210417], "area": 0.00034375, "material": "1"},
				{"coord": [0.109792, -0.261667], "area": 0.0003375, "material": "1"},
				{"coord": [0.261667, 0.105417], "area": 0.00015625, "material": "1"},
				{"coord": [-0.104792, 0.261667], "area": 0.0001625, "material": "1"},
				{"coord": [-0.261667, -0.105417], "area": 0.00015625, "material": "1"},
				{"coord": [0.268333, 0.129271], "area": 0.000171875, "material": "1"},
				{"coord": [0.268333, 0.112604], "area": 0.000171875, "material": "1"},
				{"coord": [-0.129271, 0.268333], "area": 0.000171875, "material": "1"},
				{"coord": [-0.112396, 0.268333], "area": 0.000171875, "material": "1"},
				{"coord": [-0.268333, -0.129271], "area": 0.000171875, "material": "1"},
				{"coord": [-0.268333, -0.112604], "area": 0.000171875, "material": "1"},
				{"coord": [-0.261667, 0.2075], "area": 0.0003125, "material": "1"},
				{"coord": [0.2075, 0.261667], "area": 0.0003125, "material": "1"},
				{"coord": [-0.2075, -0.261667], "area": 0.0003125, "material": "1"},
				{"coord": [0.261667, -0.2075], "area": 0.0003125, "material": "1"},
				{"coord": [0.223542, -0.268333], "area": 0.00034375, "material": "1"},
				{"coord": [0.268333, 0.223542], "area": 0.00034375, "material": "1"},
				{"coord": [-0.223542, 0.268333], "area": 0.00034375, "material": "1"},
				{"coord": [-0.268333, -0.223542], "area": 0.00034375, "material": "1"},
				{"coord": [-0.175208, -0.261667], "area": 0.0003125, "material": "1"},
				{"coord": [0.261667, -0.175208], "area": 0.0003125, "material": "1"},
				{"coord": [0.175208, 0.261667], "area": 0.0003125, "material": "1"},
				{"coord": [-0.261667, 0.175208], "area": 0.0003125, "material": "1"},
				{"coord": [0.156875, -0.268333], "area": 0.00034375, "material": "1"},
				{"coord": [0.268333, 0.156875], "area": 0.00034375, "material": "1"},
				{"coord": [-0.156875, 0.268333], "area": 0.00034375, "material": "1"},
				{"coord": [-0.268333, -0.156875], "area": 0.00034375, "material": "1"},
				{"coord": [-0.261667, -0.239792], "area": 0.0003125, "material": "1"},
				{"coord": [0.239792, -0.261667], "area": 0.0003125, "material": "1"},
				{"coord": [-0.239792, 0.261667], "area": 0.0003125, "material": "1"},
				{"coord": [0.261667, 0.239792], "area": 0.0003125, "material": "1"},
				{"coord": [-0.256875, -0.268333], "area": 0.00034375, "material": "1"},
				{"coord": [0.268333, -0.256875], "area": 0.00034375, "material": "1"},
				{"coord": [0.256875, 0.268333], "area": 0.00034375, "material": "1"},
				{"coord": [-0.268333, 0.256875], "area": 0.00034375, "material": "1"},
				{"coord": [0.148534, -0.162875], "area": 0.00139058, "material": "2"},
				{"coord": [0.236679, 0.00458333], "area": 0.000446379, "material": "2"},
				{"coord": [-0.202492, -0.120439], "area": 0.000927496, "material": "2"},
				{"coord": [-0.11375, 0.239451], "area": 0.000189506, "material": "2"},
				{"coord": [-0.020625, -0.243564], "area": 0.000536084, "material": "2"},
				{"coord": [0.240049, 0.114375], "area": 0.000175209, "material": "2"},
				{"coord": [-0.0325, 0.235283], "area": 0.0004806, "material": "2"},
				{"coord": [-0.235469, 0.16125], "area": 0.000457764, "material": "2"},
				{"coord": [-0.245101, -0.051875], "area": 0.000463996, "material": "2"},
				{"coord": [-0.176875, -0.236534], "area": 0.000865588, "material": "2"},
				{"coord": [0.236534, 0.176875], "area": 0.000865588, "material": "2"},
				{"coord": [0.243564, -0.145625], "area": 0.000536084, "material": "2"},
				{"coord": [-0.0675, -0.225098], "area": 0.000700836, "material": "2"},
				{"coord": [0.129583, -0.22498], "area": 0.000738214, "material": "2"},
				{"coord": [0.239375, -0.211095], "area": 0.000732422, "material": "2"},
				{"coord": [-0.083125, -0.243564], "area": 0.000536084, "material": "2"},
				{"coord": [0.225098, 0.1925], "area": 0.000700836, "material": "2"},
				{"coord": [-0.228958, 0.228958], "area": 0.000976563, "material": "2"},
				{"coord": [0.176875, 0.241398], "area": 0.000637591, "material": "2"},
				{"coord": [-0.211095, -0.239375], "area": 0.000732422, "material": "2"},
				{"coord": [-0.228958, 0.1925], "area": 0.000610352, "material": "2"},
				{"coord": [0.236534, -0.176875], "area": 0.000865588, "material": "2"},
				{"coord": [-0.239277, -0.0675], "area": 0.000368499, "material": "2"},
				{"coord": [0.113125, -0.243446], "area": 0.000584921, "material": "2"},
				{"coord": [0.239277, 0.0675], "area": 0.000368499, "material": "2"},
				{"coord": [-0.065, 0.238648], "area": 0.000398569, "material": "2"},
				{"coord": [0.225098, -0.16125], "area": 0.000700836, "material": "2"},
				{"coord": [-0.232802, -0.1925], "area": 0.000520261, "material": "2"},
				{"coord": [0.245767, 0.122188], "area": 0.000216397, "material": "2"},
				{"coord": [0.176875, -0.245457], "area": 0.00044732, "material": "2"},
				{"coord": [-0.121875, 0.245398], "area": 0.000234055, "material": "2"},
				{"coord": [0.0975, 0.223902], "area": 0.000758024, "material": "2"},
				{"coord": [-0.240049, -0.114375], "area": 0.000175209, "material": "2"},
				{"coord": [-0.1925, 0.228958], "area": 0.000610352, "material": "2"},
				{"coord": [0.208125, -0.242345], "area": 0.000593201, "material": "2"},
				{"coord": [0.243564, 0.208125], "area": 0.000536084, "material": "2"},
				{"coord": [-0.208125, 0.239375], "area": 0.000732422, "material": "2"},
				{"coord": [-0.242345, -0.208125], "area": 0.000593201, "material": "2"},
				{"coord": [0.0929593, -0.148313], "area": 0.00225271, "material": "2"},
				{"coord": [0.236041, 0.03625], "area": 0.000444342, "material": "2"},
				{"coord": [0.245739, -0.011875], "area": 0.000468824, "material": "2"},
				{"coord": [0.245101, 0.051875], "area": 0.000463996, "material": "2"},
				{"coord": [0.198678, -0.153511], "area": 0.00078236, "material": "2"},
				{"coord": [0.249176, 0.083125], "area": 0.000273003, "material": "2"},
				{"coord": [-0.08125, 0.248943], "area": 0.00029528, "material": "2"},
				{"coord": [-0.249176, -0.083125], "area": 0.000273003, "material": "2"},
				{"coord": [-0.051875, -0.236534], "area": 0.000865588, "material": "2"},
				{"coord": [0.04875, 0.243106], "area": 0.000579829, "material": "2"},
				{"coord": [-0.159275, 0.193074], "area": 0.00108427, "material": "2"},
				{"coord": [0.205755, 0.117679], "area": 0.000704935, "material": "2"},
				{"coord": [0.1925, -0.232802], "area": 0.000520261, "material": "2"},
				{"coord": [0.154586, 0.20362], "area": 0.000901813, "material": "2"},
				{"coord": [-0.216737, 0.124054], "area": 0.000518829, "material": "2"},
				{"coord": [-0.245767, -0.122187], "area": 0.000216397, "material": "2"},
				{"coord": [0.245767, 0.137813], "area": 0.000432794, "material": "2"},
				{"coord": [0.08125, 0.235795], "area": 0.00093622, "material": "2"},
				{"coord": [0.249282, 0.106563], "area": 0.000134021, "material": "2"},
				{"coord": [0.22334, 0.108144], "area": 0.000314941, "material": "2"},
				{"coord": [0.243458, 0.0961458], "area": 0.000202272, "material": "2"},
				{"coord": [-0.137708, 0.245398], "area": 0.000450106, "material": "2"},
				{"coord": [-0.242649, 0.079375], "area": 0.000625289, "material": "2"},
				{"coord": [-0.105625, 0.249053], "area": 0.000144957, "material": "2"},
				{"coord": [-0.10727, 0.222074], "area": 0.00034064, "material": "2"},
				{"coord": [-0.0947917, 0.242996], "area": 0.000218777, "material": "2"},
				{"coord": [-0.245767, -0.137812], "area": 0.000432794, "material": "2"},
				{"coord": [-0.16125, -0.225098], "area": 0.000700836, "material": "2"},
				{"coord": [-0.249282, -0.106562], "area": 0.000134021, "material": "2"},
				{"coord": [-0.22334, -0.108144], "area": 0.000314941, "material": "2"},
				{"coord": [-0.243458, -0.0961458], "area": 0.000202272, "material": "2"},
				{"coord": [0.227301, 0.153438], "area": 0.00129838, "material": "2"},
				{"coord": [-0.04875, 0.244705], "area": 0.000501858, "material": "2"},
				{"coord": [0.226749, 0.0951236], "area": 0.000384651, "material": "2"},
				{"coord": [0.222569, 0.0768944], "area": 0.000586963, "material": "2"},
				{"coord": [-0.184688, 0.200313], "area": 0.000915527, "material": "2"},
				{"coord": [-0.236041, -0.03625], "area": 0.000444342, "material": "2"},
				{"coord": [-0.0937285, 0.225619], "area": 0.000416038, "material": "2"},
				{"coord": [-0.0747702, 0.221272], "area": 0.000634859, "material": "2"},
				{"coord": [-0.245457, -0.176875], "area": 0.00044732, "material": "2"},
				{"coord": [0.00104167, -0.243564], "area": 0.000578971, "material": "2"},
				{"coord": [-0.226749, -0.0951236], "area": 0.000384651, "material": "2"},
				{"coord": [-0.222569, -0.0768944], "area": 0.000586963, "material": "2"},
				{"coord": [-0.239375, 0.208125], "area": 0.000732422, "material": "2"},
				{"coord": [0.196689, 0.225773], "area": 0.000941381, "material": "2"},
				{"coord": [-0.19547, -0.220909], "area": 0.00104581, "material": "2"},
				{"coord": [0.220909, -0.19547], "area": 0.00104581, "material": "2"},
				{"coord": [0.244583, -0.244583], "area": 0.000488281, "material": "2"},
				{"coord": [0.244583, 0.244583], "area": 0.000488281, "material": "2"},
				{"coord": [-0.244583, 0.244583], "area": 0.000488281, "material": "2"},
				{"coord": [-0.244583, -0.244583], "area": 0.000488281, "material": "2"},
				{"coord": [0.216782, 0.00457394], "area": 0.000523619, "material": "2"},
				{"coord": [0.24594, 0.020625], "area": 0.000424687, "material": "2"},
				{"coord": [0.0243013, 0.166054], "area": 0.00102653, "material": "2"},
				{"coord": [-0.01625, 0.245578], "area": 0.000459342, "material": "2"},
				{"coord": [-0.197259, -0.0295457], "area": 0.000968422, "material": "2"},
				{"coord": [-0.24594, -0.020625], "area": 0.000424687, "material": "2"},
				{"coord": [0.243564, -0.123958], "area": 0.000578971, "material": "2"},
				{"coord": [0.145625, -0.236534], "area": 0.000865588, "material": "2"},
				{"coord": [-0.145625, -0.243564], "area": 0.000536084, "material": "2"},
				{"coord": [-0.236224, -0.153437], "area": 0.000775547, "material": "2"},
				{"coord": [-0.244583, 0.176875], "area": 0.000488281, "material": "2"},
				{"coord": [-0.176875, 0.244583], "area": 0.000488281, "material": "2"},
				{"coord": [-0.231928, -0.228958], "area": 0.000837342, "material": "2"},
				{"coord": [-0.192849, -0.173308], "area": 0.00140763, "material": "2"},
				{"coord": [0.199056, 0.199731], "area": 0.000748613, "material": "2"},
				{"coord": [0.203997, 0.144743], "area": 0.000974513, "material": "2"},
				{"coord": [5.55112e-17, 0.236196], "area": 0.000458358, "material": "2"},
				{"coord": [-0.0254952, 0.194943], "area": 0.00104998, "material": "2"},
				{"coord": [-0.235984, 0.02875], "area": 0.000481344, "material": "2"},
				{"coord": [-0.236679, -0.00458333], "area": 0.000446379, "material": "2"},
				{"coord": [-0.03625, -0.225098], "area": 0.000700836, "material": "2"},
				{"coord": [0.103969, 0.168781], "area": 0.00165263, "material": "2"},
				{"coord": [0.200448, 0.0597828], "area": 0.00139105, "material": "2"},
				{"coord": [0.242649, -0.079375], "area": 0.000625289, "material": "2"},
				{"coord": [-0.0569741, 0.198266], "area": 0.00150456, "material": "2"},
				{"coord": [0.065, 0.223902], "area": 0.000758024, "material": "2"},
				{"coord": [-0.200448, -0.0597828], "area": 0.00139105, "material": "2"},
				{"coord": [-0.2135, 0.10197], "area": 0.000546866, "material": "2"},
				{"coord": [0.180139, -0.106761], "area": 0.00159287, "material": "2"},
				{"coord": [0.045625, -0.242649], "area": 0.000625289, "material": "2"},
				{"coord": [0.228958, -0.231928], "area": 0.000837342, "material": "2"},
				{"coord": [0.174034, -0.20095], "area": 0.00107758, "material": "2"},
				{"coord": [0.222705, -0.0625], "area": 0.000817455, "material": "2"},
				{"coord": [0.235057, -0.045625], "area": 0.00100962, "material": "2"},
				{"coord": [-0.114375, -0.245724], "area": 0.00043482, "material": "2"},
				{"coord": [-0.123413, -0.205465], "area": 0.000929623, "material": "2"},
				{"coord": [-0.144246, -0.196275], "area": 0.00118807, "material": "2"},
				{"coord": [-0.154138, -0.170528], "area": 0.00184655, "material": "2"},
				{"coord": [-0.245885, 0.145625], "area": 0.000427246, "material": "2"},
				{"coord": [-0.216657, 0.160119], "area": 0.000430659, "material": "2"},
				{"coord": [-0.210147, 0.180953], "area": 0.000542089, "material": "2"},
				{"coord": [-0.153333, 0.234981], "area": 0.000840287, "material": "2"},
				{"coord": [-0.206761, -0.194867], "area": 0.000667287, "material": "2"},
				{"coord": [-0.209658, -0.147503], "area": 0.00141198, "material": "2"},
				{"coord": [0.233147, 0.228958], "area": 0.000780225, "material": "2"},
				{"coord": [0.212314, 0.239375], "area": 0.000732422, "material": "2"},
				{"coord": [0.129792, 0.233554], "area": 0.000511602, "material": "2"},
				{"coord": [0.11375, 0.243106], "area": 0.000579829, "material": "2"},
				{"coord": [0.172579, 0.187131], "area": 0.0011631, "material": "2"},
				{"coord": [0.155838, 0.131315], "area": 0.00179574, "material": "2"},
				{"coord": [0.175317, 0.160788], "area": 0.0011692, "material": "2"},
				{"coord": [0.145625, 0.245448], "area": 0.000447765, "material": "2"},
				{"coord": [0.01625, 0.245618], "area": 0.000457374, "material": "2"},
				{"coord": [4.20925e-05, 0.215496], "area": 0.000550767, "material": "2"},
				{"coord": [-0.245739, 0.011875], "area": 0.000468824, "material": "2"},
				{"coord": [-0.169232, 0.0238427], "area": 0.0014271, "material": "2"},
				{"coord": [-0.0817463, -0.196275], "area": 0.00110085, "material": "2"},
				{"coord": [-0.13, -0.234287], "area": 0.000485452, "material": "2"},
				{"coord": [0.0625, -0.222705], "area": 0.000817455, "material": "2"},
				{"coord": [0.079375, -0.235057], "area": 0.00100962, "material": "2"},
				{"coord": [0.197259, 0.0295457], "area": 0.000968422, "material": "2"},
				{"coord": [0.0182391, -0.180139], "area": 0.00159287, "material": "2"},
				{"coord": [0.216144, 0.0258239], "area": 0.000527702, "material": "2"},
				{"coord": [0.225796, -0.02875], "area": 0.000739223, "material": "2"},
				{"coord": [-0.122546, 0.165739], "area": 0.000684213, "material": "2"},
				{"coord": [-0.199246, 0.0309119], "area": 0.00133883, "material": "2"},
				{"coord": [-0.0216246, 0.214583], "area": 0.000571199, "material": "2"},
				{"coord": [0.0325, 0.233724], "area": 0.000518601, "material": "2"},
				{"coord": [-0.216144, -0.0258239], "area": 0.000527702, "material": "2"},
				{"coord": [-0.245245, 0.045625], "area": 0.000493864, "material": "2"},
				{"coord": [-0.159774, -0.118041], "area": 0.00223947, "material": "2"},
				{"coord": [-0.206792, 0.0590275], "area": 0.000802377, "material": "2"},
				{"coord": [0.173657, -0.171504], "area": 0.00131942, "material": "2"},
				{"coord": [0.17696, -0.0202772], "area": 0.00138727, "material": "2"},
				{"coord": [0.112708, -0.205037], "area": 0.000758886, "material": "2"},
				{"coord": [0.09625, -0.223503], "area": 0.000797271, "material": "2"},
				{"coord": [0.194867, -0.206761], "area": 0.000667287, "material": "2"},
				{"coord": [0.16125, -0.226991], "area": 0.000656454, "material": "2"},
				{"coord": [-0.09875, -0.234287], "area": 0.000485452, "material": "2"},
				{"coord": [-0.10258, -0.205465], "area": 0.000902817, "material": "2"},
				{"coord": [-0.23668, 0.129679], "area": 0.000442549, "material": "2"},
				{"coord": [-0.189197, 0.136073], "area": 0.000517683, "material": "2"},
				{"coord": [-0.159822, 0.151398], "area": 0.000568098, "material": "2"},
				{"coord": [-0.116024, 0.205158], "area": 0.000665062, "material": "2"},
				{"coord": [0.133545, 0.205329], "area": 0.000877464, "material": "2"},
				{"coord": [0.16125, 0.231846], "area": 0.000542678, "material": "2"},
				{"coord": [0.186615, -0.0759581], "area": 0.00146939, "material": "2"},
				{"coord": [0.231212, -0.107083], "area": 0.00120426, "material": "2"},
				{"coord": [0.177043, 0.106435], "area": 0.00132916, "material": "2"},
				{"coord": [0.024505, 0.0879296], "area": 0.00280462, "material": "2"},
				{"coord": [0.000957751, 0.163817], "area": 0.00125226, "material": "2"},
				{"coord": [0.0217088, 0.213024], "area": 0.000612495, "material": "2"},
				{"coord": [-0.216782, -0.00457394], "area": 0.000523619, "material": "2"},
				{"coord": [-0.232893, 0.0625], "area": 0.000559576, "material": "2"},
				{"coord": [-0.167389, -0.00411485], "area": 0.00115413, "material": "2"},
				{"coord": [-0.216086, 0.0175094], "area": 0.00055099, "material": "2"},
				{"coord": [0.0490419, -0.186615], "area": 0.00146939, "material": "2"},
				{"coord": [0.0179167, -0.231212], "area": 0.00120426, "material": "2"},
				{"coord": [-0.0157235, -0.157129], "area": 0.00109875, "material": "2"},
				{"coord": [-0.0885492, -0.144147], "area": 0.00133616, "material": "2"},
				{"coord": [-0.245795, 0.11322], "area": 0.000466013, "material": "2"},
				{"coord": [-0.233443, 0.0963453], "area": 0.00055095, "material": "2"},
				{"coord": [-0.207131, 0.138869], "area": 0.000671428, "material": "2"},
				{"coord": [-0.191917, 0.178348], "area": 0.000795063, "material": "2"},
				{"coord": [-0.143546, 0.212118], "area": 0.0010818, "material": "2"},
				{"coord": [-0.180494, 0.154719], "area": 0.000442608, "material": "2"},
				{"coord": [0.112086, 0.195676], "area": 0.00109781, "material": "2"},
				{"coord": [0.172402, 0.0719765], "area": 0.00191342, "material": "2"},
				{"coord": [0.168958, 0.00552787], "area": 0.00103982, "material": "2"},
				{"coord": [0.205899, -0.0175094], "area": 0.000808439, "material": "2"},
				{"coord": [-0.0403904, -0.174753], "area": 0.00103675, "material": "2"},
				{"coord": [-0.145833, 0.167789], "area": 0.000675504, "material": "2"},
				{"coord": [-0.17362, 0.0863303], "area": 0.00123067, "material": "2"},
				{"coord": [-0.111923, 0.140604], "area": 0.000963201, "material": "2"},
				{"coord": [0.139951, 0.0515397], "area": 0.00176443, "material": "2"},
				{"coord": [-0.128229, -0.142324], "area": 0.0018809, "material": "2"},
				{"coord": [-0.153133, 0.126305], "area": 0.000943003, "material": "2"},
				{"coord": [-0.196604, 0.0815275], "area": 0.00100689, "material": "2"},
				{"coord": [-0.172673, 0.114715], "area": 0.00076285, "material": "2"},
				{"coord": [-0.108467, 0.184065], "area": 0.00071043, "material": "2"},
				{"coord": [-0.153795, 0.0567611], "area": 0.00123806, "material": "2"},
				{"coord": [-0.075694, 0.147243], "area": 0.00184969, "material": "2"},
				{"coord": [0.160767, -0.0562259], "area": 0.00218404, "material": "2"},
				{"coord": [-0.0285111, -0.198678], "area": 0.00078236, "material": "2"},
				{"coord": [0.0709386, 0.17018], "area": 0.00124122, "material": "2"},
				{"coord": [0.0573896, 0.197075], "area": 0.000800146, "material": "2"},
				{"coord": [-0.0507247, 0.110265], "area": 0.00428025, "material": "2"},
				{"coord": [0.139697, 0.0153282], "area": 0.00169341, "material": "2"},
				{"coord": [0.0589232, -0.146893], "area": 0.00265969, "material": "2"},
				{"coord": [0.0708565, 0.0434682], "area": 0.00201812, "material": "2"},
				{"coord": [-0.12852, 0.11756], "area": 0.00121793, "material": "2"},
				{"coord": [-0.0737918, 0.177865], "area": 0.00141324, "material": "2"},
				{"coord": [0.204793, -0.121011], "area": 0.00147849, "material": "2"},
				{"coord": [0.148902, -0.130632], "area": 0.00109342, "material": "2"},
				{"coord": [0.0303484, 0.195579], "area": 0.00100221, "material": "2"},
				{"coord": [0.0540582, 0.147964], "area": 0.00124122, "material": "2"},
				{"coord": [0.00398886, -0.204793], "area": 0.00147849, "material": "2"},
				{"coord": [-0.0270081, -0.131517], "area": 0.00194971, "material": "2"},
				{"coord": [-0.128236, 0.0764016], "area": 0.00181321, "material": "2"},
				{"coord": [-0.0846276, 0.0124258], "area": 0.00411505, "material": "2"},
				{"coord": [0.115411, -0.117547], "area": 0.00176515, "material": "2"},
				{"coord": [0.116411, -0.18192], "area": 0.00156295, "material": "2"},
				{"coord": [0.0624023, 0.116814], "area": 0.00160447, "material": "2"},
				{"coord": [0.123941, 0.132471], "area": 0.00212147, "material": "2"},
				{"coord": [0.0168358, -0.114806], "area": 0.00292521, "material": "2"},
				{"coord": [-0.121401, -0.0619674], "area": 0.00295063, "material": "2"},
				{"coord": [-0.067432, -0.120938], "area": 0.00123124, "material": "2"},
				{"coord": [-0.0727922, -0.17235], "area": 0.00141101, "material": "2"},
				{"coord": [-0.0799756, -0.0843401], "area": 0.00194027, "material": "2"},
				{"coord": [-0.158395, -0.0808219], "area": 0.0037031, "material": "2"},
				{"coord": [0.099255, 0.102719], "area": 0.00204691, "material": "2"},
				{"coord": [0.105297, 0.0679658], "area": 0.00187588, "material": "2"},
				{"coord": [0.121739, -0.052626], "area": 0.00262306, "material": "2"},
				{"coord": [0.0744843, 0.00483695], "area": 0.00212508, "material": "2"},
				{"coord": [0.0269172, 0.0493372], "area": 0.00259722, "material": "2"},
				{"coord": [-0.133584, -0.0154975], "area": 0.0023016, "material": "2"},
				{"coord": [-0.00718269, 0.116844], "area": 0.00332026, "material": "2"},
				{"coord": [0.0442208, -0.0545151], "area": 0.00316546, "material": "2"},
				{"coord": [-0.0866689, 0.062467], "area": 0.00433117, "material": "2"},
				{"coord": [-0.053824, -0.0559893], "area": 0.00240408, "material": "2"},
				{"coord": [-0.0462932, -0.00569335], "area": 0.00301489, "material": "2"},
				{"coord": [0.100027, -0.0788265], "area": 0.00229086, "material": "2"},
				{"coord": [0.00256348, -0.075876], "area": 0.00421076, "material": "2"},
				{"coord": [-0.00238024, 0.0123343], "area": 0.00247856, "material": "2"},
				{"coord": [0.10867, -0.00687701], "area": 0.00194057, "material": "2"},
				{"coord": [0.0317464, -0.0166006], "area": 0.00236067, "material": "2"},
				{"coord": [-0.249, -0.249], "area": 0.000113097, "material": "3"},
				{"coord": [-0.249, -0.177857], "area": 0.000113097, "material": "3"},
				{"coord": [-0.249, -0.106714], "area": 0.000113097, "material": "3"},
				{"coord": [-0.249, -0.0355714], "area": 0.000113097, "material": "3"},
				{"coord": [-0.249, 0.0355714], "area": 0.000113097, "material": "3"},
				{"coord": [-0.249, 0.106714], "area": 0.000113097, "material": "3"},
				{"coord": [-0.249, 0.177857], "area": 0.000113097, "material": "3"},
				{"coord": [-0.249, 0.249], "area": 0.000113097, "material": "3"},
				{"coord": [-0.177857, 0.249], "area": 0.000113097, "material": "3"},
				{"coord": [-0.106714, 0.249], "area": 0.000113097, "material": "3"},
				{"coord": [-0.0355714, 0.249], "area": 0.000113097, "material": "3"},
				{"coord": [0.0355714, 0.249], "area": 0.000113097, "material": "3"},
				{"coord": [0.106714, 0.249], "area": 0.000113097, "material": "3"},
				{"coord": [0.177857, 0.249], "area": 0.000113097, "material": "3"},
				{"coord": [0.249, 0.249], "area": 0.000113097, "material": "3"},
				{"coord": [0.249, 0.177857], "area": 0.000113097, "material": "3"},
				{"coord": [0.249, 0.106714], "area": 0.000113097, "material": "3"},
				{"coord": [0.249, 0.0355714], "area": 0.000113097, "material": "3"},
				{"coord": [0.249, -0.0355714], "area": 0.000113097, "material": "3"},
				{"coord": [0.249, -0.106714], "area": 0.000113097, "material": "3"},
				{"coord": [0.249, -0.177857], "area": 0.000113097, "material": "3"},
				{"coord": [0.249, -0.249], "area": 0.000113097, "material": "3"},
				{"coord": [0.177857, -0.249], "area": 0.000113097, "material": "3"},
				{"coord": [0.106714, -0.249], "area": 0.000113097, "material": "3"},
				{"coord": [0.0355714, -0.249], "area": 0.000113097, "material": "3"},
				{"coord": [-0.0355714, -0.249], "area": 0.000113097, "material": "3"},
				{"coord": [-0.106714, -0.249], "area": 0.000113097, "material": "3"},
				{"coord": [-0.177857, -0.249], "area": 0.000113097, "material": "3"},
				{"coord": [-0.249, -0.249], "area": 0.000113097, "material": "3"}
			]},
			{"name": "200", "type": "FiberSection3d", "torsion": 31292, "fibers": [
				{"coord": [-0.166795, -0.0966911], "area": 0.000312869, "material": "5"},
				{"coord": [-0.138108, -0.124834], "area": 0.000281582, "material": "5"},
				{"coord": [-0.149616, -0.121593], "area": 0.000312869, "material": "5"},
				{"coord": [-0.124834, -0.138108], "area": 0.000281582, "material": "5"},
				{"coord": [-0.155936, -0.101692], "area": 0.000281582, "material": "5"},
				{"coord": [-0.186313, -0.0495711], "area": 0.000312869, "material": "5"},
				{"coord": [-0.182171, -0.0383561], "area": 0.000281582, "material": "5"},
				{"coord": [-0.173928, -0.0663816], "area": 0.000281582, "material": "5"},
				{"coord": [-0.176265, -0.0781066], "area": 0.000312869, "material": "5"},
				{"coord": [-0.191774, -0.019815], "area": 0.000312869, "material": "5"},
				{"coord": [-0.0781066, -0.176265], "area": 0.000312869, "material": "5"},
				{"coord": [-0.019815, -0.191774], "area": 0.000312869, "material": "5"},
				{"coord": [0.00938607, -0.185928], "area": 0.000281582, "material": "5"},
				{"coord": [-0.0495711, -0.186313], "area": 0.000312869, "material": "5"},
				{"coord": [-0.00938607, -0.185928], "area": 0.000281582, "material": "5"},
				{"coord": [-0.121593, -0.149616], "area": 0.000312869, "material": "5"},
				{"coord": [-0.101692, -0.155936], "area": 0.000281582, "material": "5"},
				{"coord": [-0.0966911, -0.166795], "area": 0.000312869, "material": "5"},
				{"coord": [-0.0663816, -0.173928], "area": 0.000281582, "material": "5"},
				{"coord": [-0.0383561, -0.182171], "area": 0.000281582, "material": "5"},
				{"coord": [-0.191774, 0.019815], "area": 0.000312869, "material": "5"},
				{"coord": [-0.182171, 0.0383561], "area": 0.000281582, "material": "5"},
				{"coord": [-0.185928, 0.00938607], "area": 0.000281582, "material": "5"},
				{"coord": [-0.185928, -0.00938607], "area": 0.000281582, "material": "5"},
				{"coord": [-0.186313, 0.0495711], "area": 0.000312869, "material": "5"},
				{"coord": [-0.176265, 0.0781066], "area": 0.000312869, "material": "5"},
				{"coord": [-0.155936, 0.101692], "area": 0.000281582, "material": "5"},
				{"coord": [-0.166795, 0.0966911], "area": 0.000312869, "material": "5"},
				{"coord": [-0.149616, 0.121593], "area": 0.000312869, "material": "5"},
				{"coord": [-0.173928, 0.0663816], "area": 0.000281582, "material": "5"},
				{"coord": [-0.124834, 0.138108], "area": 0.000281582, "material": "5"},
				{"coord": [-0.138108, 0.124834], "area": 0.000281582, "material": "5"},
				{"coord": [-0.101692, 0.155936], "area": 0.000281582, "material": "5"},
				{"coord": [-0.121593, 0.149616], "area": 0.000312869, "material": "5"},
				{"coord": [-0.0966911, 0.166795], "area": 0.000312869, "material": "5"},
				{"coord": [-0.0781066, 0.176265], "area": 0.000312869, "material": "5"},
				{"coord": [-0.0383561, 0.182171], "area": 0.000281582, "material": "5"},
				{"coord": [-0.019815, 0.191774], "area": 0.000312869, "material": "5"},
				{"coord": [-0.0495711, 0.186313], "area": 0.000312869, "material": "5"},
				{"coord": [-0.0663816, 0.173928], "area": 0.000281582, "material": "5"},
				{"coord": [0.0383561, -0.182171], "area": 0.000281582, "material": "5"},
				{"coord": [0.019815, -0.191774], "area": 0.000312869, "material": "5"},
				{"coord": [0.0663816, -0.173928], "area": 0.000281582, "material": "5"},
				{"coord": [0.0495711, -0.186313], "area": 0.000312869, "material": "5"},
				{"coord": [0.0781066, -0.176265], "area": 0.000312869, "material": "5"},
				{"coord": [0.101692, -0.155936], "area": 0.000281582, "material": "5"},
				{"coord": [0.124834, -0.138108], "area": 0.000281582, "material": "5"},
				{"coord": [0.138108, -0.124834], "area": 0.000281582, "material": "5"},
				{"coord": [0.121593, -0.149616], "area": 0.000312869, "material": "5"},
				{"coord": [0.0966911, -0.166795], "area": 0.000312869, "material": "5"},
				{"coord": [0.155936, -0.101692], "area": 0.000281582, "material": "5"},
				{"coord": [0.176265, -0.0781066], "area": 0.000312869, "material": "5"},
				{"coord": [0.166795, -0.0966911], "area": 0.000312869, "material": "5"},
				{"coord": [0.149616, -0.121593], "area": 0.000312869, "material": "5"},
				{"coord": [0.173928, -0.0663816], "area": 0.000281582, "material": "5"},
				{"coord": [0.182171, -0.0383561], "area": 0.000281582, "material": "5"},
				{"coord": [0.185928, -0.00938607], "area": 0.000281582, "material": "5"},
				{"coord": [0.191774, -0.019815], "area": 0.000312869, "material": "5"},
				{"coord": [0.185928, 0.00938607], "area": 0.000281582, "material": "5"},
				{"coord": [0.186313, -0.0495711], "area": 0.000312869, "material": "5"},
				{"coord": [0.0383561, 0.182171], "area": 0.000281582, "material": "5"},
				{"coord": [0.101692, 0.155936], "area": 0.000281582, "material": "5"},
				{"coord": [0.121593, 0.149616], "area": 0.000312869, "material": "5"},
				{"coord": [0.0663816, 0.173928], "area": 0.000281582, "material": "5"},
				{"coord": [0.0966911, 0.166795], "area": 0.000312869, "material": "5"},
				{"coord": [-0.00938607, 0.185928], "area": 0.000281582, "material": "5"},
				{"coord": [0.00938607, 0.185928], "area": 0.000281582, "material": "5"},
				{"coord": [0.019815, 0.191774], "area": 0.000312869, "material": "5"},
				{"coord": [0.0495711, 0.186313], "area": 0.000312869, "material": "5"},
				{"coord": [0.0781066, 0.176265], "area": 0.000312869, "material": "5"},
				{"coord": [0.173928, 0.0663816], "area": 0.000281582, "material": "5"},
				{"coord": [0.186313, 0.0495711], "area": 0.000312869, "material": "5"},
				{"coord": [0.191774, 0.019815], "area": 0.000312869, "material": "5"},
				{"coord": [0.182171, 0.0383561], "area": 0.000281582, "material": "5"},
				{"coord": [0.176265, 0.0781066], "area": 0.000312869, "material": "5"},
				{"coord": [0.124834, 0.138108], "area": 0.000281582, "material": "5"},
				{"coord": [0.138108, 0.124834], "area": 0.000281582, "material": "5"},
				{"coord": [0.155936, 0.101692], "area": 0.000281582, "material": "5"},
				{"coord": [0.166795, 0.0966911], "area": 0.000312869, "material": "5"},
				{"coord": [0.149616, 0.121593], "area": 0.000312869, "material": "5"},
				{"coord": [-0.169632, -0.00542181], "area": 0.000419894, "material": "6"},
				{"coord": [-0.132053, -0.0546983], "area": 0.000482286, "material": "6"},
				{"coord": [-0.0112144, 0.142493], "area": 0.000482286, "material": "6"},
				{"coord": [-0.121854, 0.0497725], "area": 0.000582645, "material": "6"},
				{"coord": [-0.145082, -0.0889065], "area": 0.000393538, "material": "6"},
				{"coord": [-0.149275, -0.0567362], "area": 0.000705011, "material": "6"},
				{"coord": [-0.0721804, -0.153605], "area": 0.000419894, "material": "6"},
				{"coord": [-0.138366, -0.0108896], "area": 0.000776764, "material": "6"},
				{"coord": [-0.102499, 0.0369972], "area": 0.000814412, "material": "6"},
				{"coord": [-0.148682, 0.0818422], "area": 0.000419894, "material": "6"},
				{"coord": [-0.157204, 0.0651161], "area": 0.000393538, "material": "6"},
				{"coord": [0.0889065, -0.145082], "area": 0.000393538, "material": "6"},
				{"coord": [-0.0567362, -0.149275], "area": 0.000705011, "material": "6"},
				{"coord": [-0.153605, -0.0721804], "area": 0.000419894, "material": "6"},
				{"coord": [-0.104094, -0.134048], "area": 0.000419894, "material": "6"},
				{"coord": [0.0564718, 0.135633], "area": 0.0012041, "material": "6"},
				{"coord": [-0.0693262, 0.111891], "area": 0.000582645, "material": "6"},
				{"coord": [-0.0546983, -0.132053], "area": 0.000482286, "material": "6"},
				{"coord": [-0.0397223, -0.165455], "area": 0.000393538, "material": "6"},
				{"coord": [-0.158762, -0.017217], "area": 0.000705011, "material": "6"},
				{"coord": [-0.154114, 0.0418409], "area": 0.000705011, "material": "6"},
				{"coord": [-0.134048, -0.104094], "area": 0.000419894, "material": "6"},
				{"coord": [-0.166695, 0.0318913], "area": 0.000419894, "material": "6"},
				{"coord": [-0.0889065, -0.145082], "area": 0.000393538, "material": "6"},
				{"coord": [-0.165455, -0.0397223], "area": 0.000393538, "material": "6"},
				{"coord": [-0.169632, 0.0133503], "area": 0.000393538, "material": "6"},
				{"coord": [-0.116114, 0.123782], "area": 0.000419894, "material": "6"},
				{"coord": [-0.0928279, 0.108687], "area": 0.000482286, "material": "6"},
				{"coord": [0.0211812, -0.168392], "area": 0.000419894, "material": "6"},
				{"coord": [-0.109308, -0.0692885], "area": 0.000743339, "material": "6"},
				{"coord": [-0.129388, 0.110508], "area": 0.000393538, "material": "6"},
				{"coord": [-0.104005, -0.0303642], "area": 0.000854808, "material": "6"},
				{"coord": [-0.100088, 0.124436], "area": 0.000705011, "material": "6"},
				{"coord": [0.0889065, 0.145082], "area": 0.000393538, "material": "6"},
				{"coord": [-0.0889065, 0.145082], "area": 0.000393538, "material": "6"},
				{"coord": [0.0721804, -0.153605], "area": 0.000419894, "material": "6"},
				{"coord": [-0.111893, -0.0952118], "area": 0.0012041, "material": "6"},
				{"coord": [-0.133642, 0.0874171], "area": 0.000705011, "material": "6"},
				{"coord": [0.142493, -0.0112144], "area": 0.000482286, "material": "6"},
				{"coord": [0.10627, 0.0821097], "area": 0.000764487, "material": "6"},
				{"coord": [0.169632, 0.0133503], "area": 0.000393538, "material": "6"},
				{"coord": [-0.0117952, -0.146445], "area": 0.0012041, "material": "6"},
				{"coord": [0.100088, -0.124436], "area": 0.000705011, "material": "6"},
				{"coord": [0.0546983, -0.132053], "area": 0.000482286, "material": "6"},
				{"coord": [0.0806823, -0.0582185], "area": 0.00143149, "material": "6"},
				{"coord": [0.165455, -0.0397223], "area": 0.000393538, "material": "6"},
				{"coord": [0.169632, -0.00542181], "area": 0.000419894, "material": "6"},
				{"coord": [0.0133503, 0.169632], "area": 0.000393538, "material": "6"},
				{"coord": [0.0721804, 0.153605], "area": 0.000419894, "material": "6"},
				{"coord": [0.147276, 0.0390084], "area": 0.00106827, "material": "6"},
				{"coord": [0.128651, -0.0825863], "area": 0.00073727, "material": "6"},
				{"coord": [0.129388, 0.110508], "area": 0.000393538, "material": "6"},
				{"coord": [0.159654, -0.0575756], "area": 0.000419894, "material": "6"},
				{"coord": [0.158762, -0.017217], "area": 0.000705011, "material": "6"},
				{"coord": [-0.024778, 0.0516741], "area": 0.0017366, "material": "6"},
				{"coord": [0.150366, 0.0622836], "area": 0.000707136, "material": "6"},
				{"coord": [0.0928279, 0.108687], "area": 0.000482286, "material": "6"},
				{"coord": [-0.00542181, 0.169632], "area": 0.000419894, "material": "6"},
				{"coord": [-0.0397223, 0.165455], "area": 0.000393538, "material": "6"},
				{"coord": [-0.127837, -0.031357], "area": 0.000582645, "material": "6"},
				{"coord": [-0.118341, 0.0725196], "area": 0.000776764, "material": "6"},
				{"coord": [-0.131169, 0.0109728], "area": 0.000582645, "material": "6"},
				{"coord": [-0.138984, 0.0333672], "area": 0.000482286, "material": "6"},
				{"coord": [-0.0721804, 0.153605], "area": 0.000419894, "material": "6"},
				{"coord": [0.0561738, 0.0832715], "area": 0.00145781, "material": "6"},
				{"coord": [-0.0211812, -0.168392], "area": 0.000419894, "material": "6"},
				{"coord": [0.116114, 0.123782], "area": 0.000419894, "material": "6"},
				{"coord": [-0.0692885, -0.109308], "area": 0.000743339, "material": "6"},
				{"coord": [0.100088, 0.124436], "area": 0.000705011, "material": "6"},
				{"coord": [0.0659381, 0.111361], "area": 0.000743339, "material": "6"},
				{"coord": [-0.0952118, -0.111893], "area": 0.0012041, "material": "6"},
				{"coord": [0.0318913, 0.166695], "area": 0.000419894, "material": "6"},
				{"coord": [0.140422, 0.0953209], "area": 0.000419894, "material": "6"},
				{"coord": [-0.0282983, -0.126287], "area": 0.000743339, "material": "6"},
				{"coord": [0.0397223, -0.165455], "area": 0.000393538, "material": "6"},
				{"coord": [0.0567362, -0.149275], "area": 0.000705011, "material": "6"},
				{"coord": [0.131723, 0.0765568], "area": 0.00106827, "material": "6"},
				{"coord": [-0.017217, 0.158762], "area": 0.000705011, "material": "6"},
				{"coord": [-0.0915259, -0.0536909], "area": 0.000991956, "material": "6"},
				{"coord": [-0.0914889, -0.00730088], "area": 0.000989336, "material": "6"},
				{"coord": [0.0682219, -0.112567], "area": 0.000582645, "material": "6"},
				{"coord": [-0.0247143, -0.0969801], "area": 0.00139234, "material": "6"},
				{"coord": [0.0282983, -0.126287], "area": 0.000743339, "material": "6"},
				{"coord": [0.0117952, -0.146445], "area": 0.0012041, "material": "6"},
				{"coord": [0.116114, -0.123782], "area": 0.000419894, "material": "6"},
				{"coord": [0.140422, -0.0953209], "area": 0.000419894, "material": "6"},
				{"coord": [0.166695, 0.0318913], "area": 0.000419894, "material": "6"},
				{"coord": [0.133204, 0.0170838], "area": 0.000764487, "material": "6"},
				{"coord": [0.084485, 0.0642864], "area": 0.00178158, "material": "6"},
				{"coord": [0.129388, -0.110508], "area": 0.000393538, "material": "6"},
				{"coord": [0.128892, -0.0377113], "area": 0.000764487, "material": "6"},
				{"coord": [0.139361, -0.0615672], "area": 0.00106827, "material": "6"},
				{"coord": [-0.0567362, 0.149275], "area": 0.000705011, "material": "6"},
				{"coord": [-0.0531141, 0.128229], "area": 0.000776764, "material": "6"},
				{"coord": [-0.0300976, 0.12814], "area": 0.000582645, "material": "6"},
				{"coord": [0.0267534, -0.102684], "area": 0.000991956, "material": "6"},
				{"coord": [0.0121116, 0.128851], "area": 0.000743339, "material": "6"},
				{"coord": [0.0340361, 0.142922], "area": 0.0012041, "material": "6"},
				{"coord": [-0.0996681, 0.0859762], "area": 0.000582645, "material": "6"},
				{"coord": [-0.0201628, 0.106455], "area": 0.000854808, "material": "6"},
				{"coord": [-0.108123, 0.0135688], "area": 0.000814412, "material": "6"},
				{"coord": [-0.0794982, 0.0745308], "area": 0.000814412, "material": "6"},
				{"coord": [0.0983552, -0.0319576], "area": 0.00202798, "material": "6"},
				{"coord": [0.0520722, -0.0950137], "area": 0.000854808, "material": "6"},
				{"coord": [0.100509, -0.0849914], "area": 0.000582645, "material": "6"},
				{"coord": [0.0901394, -0.10554], "area": 0.000776764, "material": "6"},
				{"coord": [-0.0510996, -0.0860509], "area": 0.00139234, "material": "6"},
				{"coord": [0.00628701, 0.105925], "area": 0.000991956, "material": "6"},
				{"coord": [-0.0788164, 0.0482987], "area": 0.000958079, "material": "6"},
				{"coord": [-0.0598951, -0.0570113], "area": 0.00124234, "material": "6"},
				{"coord": [-0.0381767, -0.027766], "area": 0.00188808, "material": "6"},
				{"coord": [-0.0611769, 0.0901786], "area": 0.000814412, "material": "6"},
				{"coord": [-0.0572909, -0.00138224], "area": 0.0017366, "material": "6"},
				{"coord": [-0.03503, 0.0848317], "area": 0.000989336, "material": "6"},
				{"coord": [0.101427, 0.00707813], "area": 0.00222105, "material": "6"},
				{"coord": [-0.0502431, 0.030789], "area": 0.00166104, "material": "6"},
				{"coord": [0.0541628, -0.0612132], "area": 0.00147588, "material": "6"},
				{"coord": [0.0305624, 0.0118094], "area": 0.0021231, "material": "6"},
				{"coord": [0.00203916, -0.0826653], "area": 0.00124234, "material": "6"},
				{"coord": [0.0206328, -0.0513922], "area": 0.00183296, "material": "6"},
				{"coord": [0.0263062, 0.0779246], "area": 0.00141993, "material": "6"},
				{"coord": [0.0750714, 0.0254526], "area": 0.00220971, "material": "6"},
				{"coord": [0.00571555, -0.0230051], "area": 0.0025163, "material": "6"},
				{"coord": [0.0101085, 0.0452963], "area": 0.00220359, "material": "6"},
				{"coord": [0.176, -2.78311e-17], "area": 5.02655e-05, "material": "7"},
				{"coord": [0.162603, 0.0673523], "area": 5.02655e-05, "material": "7"},
				{"coord": [0.124451, 0.124451], "area": 5.02655e-05, "material": "7"},
				{"coord": [0.0673523, 0.162603], "area": 5.02655e-05, "material": "7"},
				{"coord": [-1.35185e-18, 0.176], "area": 5.02655e-05, "material": "7"},
				{"coord": [-0.0673523, 0.162603], "area": 5.02655e-05, "material": "7"},
				{"coord": [-0.124451, 0.124451], "area": 5.02655e-05, "material": "7"},
				{"coord": [-0.162603, 0.0673523], "area": 5.02655e-05, "material": "7"},
				{"coord": [-0.176, -6.27736e-18], "area": 5.02655e-05, "material": "7"},
				{"coord": [-0.162603, -0.0673523], "area": 5.02655e-05, "material": "7"},
				{"coord": [-0.124451, -0.124451], "area": 5.02655e-05, "material": "7"},
				{"coord": [-0.0673523, -0.162603], "area": 5.02655e-05, "material": "7"},
				{"coord": [-4.44594e-17, -0.176], "area": 5.02655e-05, "material": "7"},
				{"coord": [0.0673523, -0.162603], "area": 5.02655e-05, "material": "7"},
				{"coord": [0.124451, -0.124451], "area": 5.02655e-05, "material": "7"},
				{"coord": [0.162603, -0.0673523], "area": 5.02655e-05, "material": "7"},
				{"coord": [0.176, -7.09387e-17], "area": 5.02655e-05, "material": "7"}
			]},
			{"name": "4001", "type": "FiberSection3d", "torsion": 3.15363, "fibers": [
				{"coord": [-0.004, -0.0457515], "area": 2.0334e-05, "material": "4001"},
				{"coord": [-0.002, -0.0457515], "area": 2.0334e-05, "material": "4001"},
				{"coord": [1.33299e-18, -0.0457515], "area": 2.0334e-05, "material": "4001"},
				{"coord": [0.002, -0.0457515], "area": 2.0334e-05, "material": "4001"},
				{"coord": [0.004, -0.0457515], "area": 2.0334e-05, "material": "4001"},
				{"coord": [-0.004, -0.0355845], "area": 2.0334e-05, "material": "4001"},
				{"coord": [-0.002, -0.0355845], "area": 2.0334e-05, "material": "4001"},
				{"coord": [9.57138e-19, -0.0355845], "area": 2.0334e-05, "material": "4001"},
				{"coord": [0.002, -0.0355845], "area": 2.0334e-05, "material": "4001"},
				{"coord": [0.004, -0.0355845], "area": 2.0334e-05, "material": "4001"},
				{"coord": [-0.004, -0.0254175], "area": 2.0334e-05, "material": "4001"},
				{"coord": [-0.002, -0.0254175], "area": 2.0334e-05, "material": "4001"},
				{"coord": [3.95445e-19, -0.0254175], "area": 2.0334e-05, "material": "4001"},
				{"coord": [0.002, -0.0254175], "area": 2.0334e-05, "material": "4001"},
				{"coord": [0.004, -0.0254175], "area": 2.0334e-05, "material": "4001"},
				{"coord": [-0.004, -0.0152505], "area": 2.0334e-05, "material": "4001"},
				{"coord": [-0.002, -0.0152505], "area": 2.0334e-05, "material": "4001"},
				{"coord": [1.21736e-19, -0.0152505], "area": 2.0334e-05, "material": "4001"},
				{"coord": [0.002, -0.0152505], "area": 2.0334e-05, "material": "4001"},
				{"coord": [0.004, -0.0152505], "area": 2.0334e-05, "material": "4001"},
				{"coord": [-0.004, -0.0050835], "area": 2.0334e-05, "material": "4001"},
				{"coord": [-0.002, -0.0050835], "area": 2.0334e-05, "material": "4001"},
				{"coord": [4.46997e-19, -0.0050835], "area": 2.0334e-05, "material": "4001"},
				{"coord": [0.002, -0.0050835], "area": 2.0334e-05, "material": "4001"},
				{"coord": [0.004, -0.0050835], "area": 2.0334e-05, "material": "4001"},
				{"coord": [-0.004, 0.0050835], "area": 2.0334e-05, "material": "4001"},
				{"coord": [-0.002, 0.0050835], "area": 2.0334e-05, "material": "4001"},
				{"coord": [5.58076e-19, 0.0050835], "area": 2.0334e-05, "material": "4001"},
				{"coord": [0.002, 0.0050835], "area": 2.0334e-05, "material": "4001"},
				{"coord": [0.004, 0.0050835], "area": 2.0334e-05, "material": "4001"},
				{"coord": [-0.004, 0.0152505], "area": 2.0334e-05, "material": "4001"},
				{"coord": [-0.002, 0.0152505], "area": 2.0334e-05, "material": "4001"},
				{"coord": [2.1951e-19, 0.0152505], "area": 2.0334e-05, "material": "4001"},
				{"coord": [0.002, 0.0152505], "area": 2.0334e-05, "material": "4001"},
				{"coord": [0.004, 0.0152505], "area": 2.0334e-05, "material": "4001"},
				{"coord": [-0.004, 0.0254175], "area": 2.0334e-05, "material": "4001"},
				{"coord": [-0.002, 0.0254175], "area": 2.0334e-05, "material": "4001"},
				{"coord": [1.22989e-18, 0.0254175], "area": 2.0334e-05, "material": "4001"},
				{"coord": [0.002, 0.0254175], "area": 2.0334e-05, "material": "4001"},
				{"coord": [0.004, 0.0254175], "area": 2.0334e-05, "material": "4001"},
				{"coord": [-0.004, 0.0355845], "area": 2.0334e-05, "material": "4001"},
				{"coord": [-0.002, 0.0355845], "area": 2.0334e-05, "material": "4001"},
				{"coord": [7.58942e-19, 0.0355845], "area": 2.0334e-05, "material": "4001"},
				{"coord": [0.002, 0.0355845], "area": 2.0334e-05, "material": "4001"},
				{"coord": [0.004, 0.0355845], "area": 2.0334e-05, "material": "4001"},
				{"coord": [-0.004, 0.0457515], "area": 2.0334e-05, "material": "4001"},
				{"coord": [-0.002, 0.0457515], "area": 2.0334e-05, "material": "4001"},
				{"coord": [4.87891e-19, 0.0457515], "area": 2.0334e-05, "material": "4001"},
				{"coord": [0.002, 0.0457515], "area": 2.0334e-05, "material": "4001"},
				{"coord": [0.004, 0.0457515], "area": 2.0334e-05, "material": "4001"}
			]},
			{"name": "4002", "type": "FiberSection3d", "torsion": 6.51561, "fibers": [
				{"coord": [-0.004, -0.09], "area": 4e-05, "material": "4001"},
				{"coord": [-0.002, -0.09], "area": 4e-05, "material": "4001"},
				{"coord": [0, -0.09], "area": 4e-05, "material": "4001"},
				{"coord": [0.002, -0.09], "area": 4e-05, "material": "4001"},
				{"coord": [0.004, -0.09], "area": 4e-05, "material": "4001"},
				{"coord": [-0.004, -0.07], "area": 4e-05, "material": "4001"},
				{"coord": [-0.002, -0.07], "area": 4e-05, "material": "4001"},
				{"coord": [3.93927e-19, -0.07], "area": 4e-05, "material": "4001"},
				{"coord": [0.002, -0.07], "area": 4e-05, "material": "4001"},
				{"coord": [0.004, -0.07], "area": 4e-05, "material": "4001"},
				{"coord": [-0.004, -0.05], "area": 4e-05, "material": "4001"},
				{"coord": [-0.002, -0.05], "area": 4e-05, "material": "4001"},
				{"coord": [9.60422e-19, -0.05], "area": 4e-05, "material": "4001"},
				{"coord": [0.002, -0.05], "area": 4e-05, "material": "4001"},
				{"coord": [0.004, -0.05], "area": 4e-05, "material": "4001"},
				{"coord": [-0.004, -0.03], "area": 4e-05, "material": "4001"},
				{"coord": [-0.002, -0.03], "area": 4e-05, "material": "4001"},
				{"coord": [3.60497e-19, -0.03], "area": 4e-05, "material": "4001"},
				{"coord": [0.002, -0.03], "area": 4e-05, "material": "4001"},
				{"coord": [0.004, -0.03], "area": 4e-05, "material": "4001"},
				{"coord": [-0.004, -0.01], "area": 4e-05, "material": "4001"},
				{"coord": [-0.002, -0.01], "area": 4e-05, "material": "4001"},
				{"coord": [7.31385e-19, -0.01], "area": 4e-05, "material": "4001"},
				{"coord": [0.002, -0.01], "area": 4e-05, "material": "4001"},
				{"coord": [0.004, -0.01], "area": 4e-05, "material": "4001"},
				{"coord": [-0.004, 0.01], "area": 4e-05, "material": "4001"},
				{"coord": [-0.002, 0.01], "area": 4e-05, "material": "4001"},
				{"coord": [5.69206e-19, 0.01], "area": 4e-05, "material": "4001"},
				{"coord": [0.002, 0.01], "area": 4e-05, "material": "4001"},
				{"coord": [0.004, 0.01], "area": 4e-05, "material": "4001"},
				{"coord": [-0.004, 0.03], "area": 4e-05, "material": "4001"},
				{"coord": [-0.002, 0.03], "area": 4e-05, "material": "4001"},
				{"coord": [8.3348e-19, 0.03], "area": 4e-05, "material": "4001"},
				{"coord": [0.002, 0.03], "area": 4e-05, "material": "4001"},
				{"coord": [0.004, 0.03], "area": 4e-05, "material": "4001"},
				{"coord": [-0.004, 0.05], "area": 4e-05, "material": "4001"},
				{"coord": [-0.002, 0.05], "area": 4e-05, "material": "4001"},
				{"coord": [1.15196e-18, 0.05], "area": 4e-05, "material": "4001"},
				{"coord": [0.002, 0.05], "area": 4e-05, "material": "4001"},
				{"coord": [0.004, 0.05], "area": 4e-05, "material": "4001"},
				{"coord": [-0.004, 0.07], "area": 4e-05, "material": "4001"},
				{"coord": [-0.002, 0.07], "area": 4e-05, "material": "4001"},
				{"coord": [1.43657e-18, 0.07], "area": 4e-05, "material": "4001"},
				{"coord": [0.002, 0.07], "area": 4e-05, "material": "4001"},
				{"coord": [0.004, 0.07], "area": 4e-05, "material": "4001"},
				{"coord": [-0.004, 0.09], "area": 4e-05, "material": "4001"},
				{"coord": [-0.002, 0.09], "area": 4e-05, "material": "4001"},
				{"coord": [1.84314e-18, 0.09], "area": 4e-05, "material": "4001"},
				{"coord": [0.002, 0.09], "area": 4e-05, "material": "4001"},
				{"coord": [0.004, 0.09], "area": 4e-05, "material": "4001"}
			]}
		],
		"crdTransformations": [
			{"name": "1", "type": "PDeltaCrdTransf3d", "vecInLocXZPlane": [-1, 0, 0]},
			{"name": "2", "type": "PDeltaCrdTransf3d", "vecInLocXZPlane": [0, 0, 1]}
		]
	},
	"geometry": {
		"nodes": [
			{"name": 1001, "ndf": 6, "crd": [0, -1.4, 1.875], "mass": [0.22022, 0.22022, 0.22022, 0, 0, 0]},
			{"name": 1002, "ndf": 6, "crd": [0, -1, 1.875], "mass": [0.22022, 0.22022, 0.22022, 0, 0, 0]},
			{"name": 1003, "ndf": 6, "crd": [0, -0.666667, 1.875], "mass": [0.22022, 0.22022, 0.22022, 0, 0, 0]},
			{"name": 1004, "ndf": 6, "crd": [0, -0.333333, 1.875], "mass": [0.22022, 0.22022, 0.22022, 0, 0, 0]},
			{"name": 1005, "ndf": 6, "crd": [0, 0, 1.875], "mass": [0.22022, 0.22022, 0.22022, 0, 0, 0]},
			{"name": 1006, "ndf": 6, "crd": [0, 0.333333, 1.875], "mass": [0.22022, 0.22022, 0.22022, 0, 0, 0]},
			{"name": 1007, "ndf": 6, "crd": [0, 0.666667, 1.875], "mass": [0.22022, 0.22022, 0.22022, 0, 0, 0]},
			{"name": 1008, "ndf": 6, "crd": [0, 0.8, 1.875], "mass": [0.22022, 0.22022, 0.22022, 0, 0, 0]},
			{"name": 1009, "ndf": 6, "crd": [0, 1, 1.875], "mass": [0.22022, 0.22022, 0.22022, 0, 0, 0]},
			{"name": 1010, "ndf": 6, "crd": [0, 1.4, 1.875], "mass": [0.22022, 0.22022, 0.22022, 0, 0, 0]},
			{"name": 2101, "ndf": 6, "crd": [0, -1, 1.6], "mass": [0.057846, 0.057846, 0.057846, 0, 0, 0]},
			{"name": 2102, "ndf": 6, "crd": [0, -1, 1.4], "mass": [0.057846, 0.057846, 0.057846, 0, 0, 0]},
			{"name": 2103, "ndf": 6, "crd": [0, -1, 1.2], "mass": [0.057846, 0.057846, 0.057846, 0, 0, 0]},
			{"name": 2104, "ndf": 6, "crd": [0, -1, 1], "mass": [0.057846, 0.057846, 0.057846, 0, 0, 0]},
			{"name": 2105, "ndf": 6, "crd": [0, -1, 0.8], "mass": [0.057846, 0.057846, 0.057846, 0, 0, 0]},
			{"name": 2106, "ndf": 6, "crd": [0, -1, 0.6], "mass": [0.057846, 0.057846, 0.057846, 0, 0, 0]},
			{"name": 2107, "ndf": 6, "crd": [0, -1, 0.4], "mass": [0.057846, 0.057846, 0.057846, 0, 0, 0]},
			{"name": 2108, "ndf": 6, "crd": [0, -1, 0.2], "mass": [0.057846, 0.057846, 0.057846, 0, 0, 0]},
			{"name": 2109, "ndf": 6, "crd": [0, -1, 0], "mass": [0.057846, 0.057846, 0.057846, 0, 0, 0]},
			{"name": 2201, "ndf": 6, "crd": [0, 1, 1.6], "mass": [0.057846, 0.057846, 0.057846, 0, 0, 0]},
			{"name": 2202, "ndf": 6, "crd": [0, 1, 1.4], "mass": [0.057846, 0.057846, 0.057846, 0, 0, 0]},
			{"name": 2203, "ndf": 6, "crd": [0, 1, 1.2], "mass": [0.057846, 0.057846, 0.057846, 0, 0, 0]},
			{"name": 2204, "ndf": 6, "crd": [0, 1, 1], "mass": [0.057846, 0.057846, 0.057846, 0, 0, 0]},
			{"name": 2205, "ndf": 6, "crd": [0, 1, 0.8], "mass": [0.057846, 0.057846, 0.057846, 0, 0, 0]},
			{"name": 2206, "ndf": 6, "crd": [0, 1, 0.6], "mass": [0.057846, 0.057846, 0.057846, 0, 0, 0]},
			{"name": 2207, "ndf": 6, "crd": [0, 1, 0.4], "mass": [0.057846, 0.057846, 0.057846, 0, 0, 0]},
			{"name": 2208, "ndf": 6, "crd": [0, 1, 0.2], "mass": [0.057846, 0.057846, 0.057846, 0, 0, 0]},
			{"name": 2209, "ndf": 6, "crd": [0, 1, 0], "mass": [0.057846, 0.057846, 0.057846, 0, 0, 0]},
			{"name": 3001, "ndf": 6, "crd": [0, 0.8, 1.6]},
			{"name": 3002, "ndf": 6, "crd": [0, -0.8, 0]},
			{"name": 4001, "ndf": 6, "crd": [0, 0.575284, 1.37528]},
			{"name": 4002, "ndf": 6, "crd": [0, 0.575284, 1.37528]},
			{"name": 4003, "ndf": 6, "crd": [0, 0.350568, 1.15057]},
			{"name": 4004, "ndf": 6, "crd": [0, 0.350568, 1.15057]},
			{"name": 4005, "ndf": 6, "crd": [0, -0.350568, 0.449432]},
			{"name": 4006, "ndf": 6, "crd": [0, -0.350568, 0.449432]},
			{"name": 4007, "ndf": 6, "crd": [0, -0.575284, 0.224716]},
			{"name": 4008, "ndf": 6, "crd": [0, -0.575284, 0.224716]}
		],
		"elements": [
			{"name": 12, "type": "ElasticBeam3d", "nodes": [1002, 2101], "E": 1.25536e+07, "G": 0.1, "A": 2.93e+07, "Jx": 0.00015, "Iy": 0.00015, "Iz": 0.00015, "massperlength": 0, "releasez": 0, "releasey": 0, "crdTransformation": "1"},
			{"name": 13, "type": "ElasticBeam3d", "nodes": [1009, 2201], "E": 1.25536e+07, "G": 0.1, "A": 2.93e+07, "Jx": 0.00015, "Iy": 0.00015, "Iz": 0.00015, "massperlength": 0, "releasez": 0, "releasey": 0, "crdTransformation": "1"},
			{"name": 100, "type": "Truss", "nodes": [1002, 2109], "A": 0.000362917, "massperlength": 0, "material": "10"},
			{"name": 200, "type": "Truss", "nodes": [1009, 2209], "A": 0.000362917, "massperlength": 0, "material": "10"},
			{"name": 1001, "type": "DispBeamColumn3d", "nodes": [1001, 1002], "sections": ["100", "100", "100", "100", "100"], "integration": {"type": "Legendre"}, "massperlength": 0, "crdTransformation": "2"},
			{"name": 1002, "type": "DispBeamColumn3d", "nodes": [1002, 1003], "sections": ["100", "100", "100", "100", "100"], "integration": {"type": "Legendre"}, "massperlength": 0, "crdTransformation": "2"},
			{"name": 1003, "type": "DispBeamColumn3d", "nodes": [1003, 1004], "sections": ["100", "100", "100", "100", "100"], "integration": {"type": "Legendre"}, "massperlength": 0, "crdTransformation": "2"},
			{"name": 1004, "type": "DispBeamColumn3d", "nodes": [1004, 1005], "sections": ["100", "100", "100", "100", "100"], "integration": {"type": "Legendre"}, "massperlength": 0, "crdTransformation": "2"},
			{"name": 1005, "type": "DispBeamColumn3d", "nodes": [1005, 1006], "sections": ["100", "100", "100", "100", "100"], "integration": {"type": "Legendre"}, "massperlength": 0, "crdTransformation": "2"},
			{"name": 1006, "type": "DispBeamColumn3d", "nodes": [1006, 1007], "sections": ["100", "100", "100", "100", "100"], "integration": {"type": "Legendre"}, "massperlength": 0, "crdTransformation": "2"},
			{"name": 1007, "type": "DispBeamColumn3d", "nodes": [1007, 1008], "sections": ["100", "100", "100", "100", "100"], "integration": {"type": "Legendre"}, "massperlength": 0, "crdTransformation": "2"},
			{"name": 1008, "type": "DispBeamColumn3d", "nodes": [1008, 1009], "sections": ["100", "100", "100", "100", "100"], "integration": {"type": "Legendre"}, "massperlength": 0, "crdTransformation": "2"},
			{"name": 1009, "type": "DispBeamColumn3d", "nodes": [1009, 1010], "sections": ["100", "100", "100", "100", "100"], "integration": {"type": "Legendre"}, "massperlength": 0, "crdTransformation": "2"},
			{"name": 2101, "type": "DispBeamColumn3d", "nodes": [2101, 2102], "sections": ["200", "200", "200", "200", "200"], "integration": {"type": "Legendre"}, "massperlength": 0, "crdTransformation": "1"},
			{"name": 2102, "type": "DispBeamColumn3d", "nodes": [2102, 2103], "sections": ["200", "200", "200", "200", "200"], "integration": {"type": "Legendre"}, "massperlength": 0, "crdTransformation": "1"},
			{"name": 2103, "type": "DispBeamColumn3d", "nodes": [2103, 2104], "sections": ["200", "200", "200", "200", "200"], "integration": {"type": "Legendre"}, "massperlength": 0, "crdTransformation": "1"},
			{"name": 2104, "type": "DispBeamColumn3d", "nodes": [2104, 2105], "sections": ["200", "200", "200", "200", "200"], "integration": {"type": "Legendre"}, "massperlength": 0, "crdTransformation": "1"},
			{"name": 2105, "type": "DispBeamColumn3d", "nodes": [2105, 2106], "sections": ["200", "200", "200", "200", "200"], "integration": {"type": "Legendre"}, "massperlength": 0, "crdTransformation": "1"},
			{"name": 2106, "type": "DispBeamColumn3d", "nodes": [2106, 2107], "sections": ["200", "200", "200", "200", "200"], "integration": {"type": "Legendre"}, "massperlength": 0, "crdTransformation": "1"},
			{"name": 2107, "type": "DispBeamColumn3d", "nodes": [2107, 2108], "sections": ["200", "200", "200", "200", "200"], "integration": {"type": "Legendre"}, "massperlength": 0, "crdTransformation": "1"},
			{"name": 2108, "type": "DispBeamColumn3d", "nodes": [2108, 2109], "sections": ["200", "200", "200", "200", "200"], "integration": {"type": "Legendre"}, "massperlength": 0, "crdTransformation": "1"},
			{"name": 2201, "type": "DispBeamColumn3d", "nodes": [2201, 2202], "sections": ["200", "200", "200", "200", "200"], "integration": {"type": "Legendre"}, "massperlength": 0, "crdTransformation": "1"},
			{"name": 2202, "type": "DispBeamColumn3d", "nodes": [2202, 2203], "sections": ["200", "200", "200", "200", "200"], "integration": {"type": "Legendre"}, "massperlength": 0, "crdTransformation": "1"},
			{"name": 2203, "type": "DispBeamColumn3d", "nodes": [2203, 2204], "sections": ["200", "200", "200", "200", "200"], "integration": {"type": "Legendre"}, "massperlength": 0, "crdTransformation": "1"},
			{"name": 2204, "type": "DispBeamColumn3d", "nodes": [2204, 2205], "sections": ["200", "200", "200", "200", "200"], "integration": {"type": "Legendre"}, "massperlength": 0, "crdTransformation": "1"},
			{"name": 2205, "type": "DispBeamColumn3d", "nodes": [2205, 2206], "sections": ["200", "200", "200", "200", "200"], "integration": {"type": "Legendre"}, "massperlength": 0, "crdTransformation": "1"},
			{"name": 2206, "type": "DispBeamColumn3d", "nodes": [2206, 2207], "sections": ["200", "200", "200", "200", "200"], "integration": {"type": "Legendre"}, "massperlength": 0, "crdTransformation": "1"},
			{"name": 2207, "type": "DispBeamColumn3d", "nodes": [2207, 2208], "sections": ["200", "200", "200", "200", "200"], "integration": {"type": "Legendre"}, "massperlength": 0, "crdTransformation": "1"},
			{"name": 2208, "type": "DispBeamColumn3d", "nodes": [2208, 2209], "sections": ["200", "200", "200", "200", "200"], "integration": {"type": "Legendre"}, "massperlength": 0, "crdTransformation": "1"},
			{"name": 4001, "type": "ElasticBeam3d", "nodes": [3001, 4001], "E": 8e+07, "G": 0.002, "A": 2e+08, "Jx": 1e+08, "Iy": 1e+08, "Iz": 1e+08, "massperlength": 0, "releasez": 0, "releasey": 0, "crdTransformation": "2"},
			{"name": 4002, "type": "ZeroLength", "nodes": [4001, 4002], "materials": ["4015", "4003", "4003", "4003", "4003", "4003"], "dof": ["P", "Vy", "Vz", "T", "My", "Mz"], "transMatrix": [[0, -0.707107, -0.707107], [0, -0.707107, 0.707107], [-1, -0, 0]]},
			{"name": 4003, "type": "ElasticBeam3d", "nodes": [4002, 4003], "E": 8e+07, "G": 0.002, "A": 2e+08, "Jx": 1e+08, "Iy": 1e+08, "Iz": 1e+08, "massperlength": 0, "releasez": 0, "releasey": 0, "crdTransformation": "2"},
			{"name": 4004, "type": "ZeroLength", "nodes": [4003, 4004], "materials": ["4003", "4003", "4003", "4003", "4002", "4002"], "dof": ["P", "Vy", "Vz", "T", "My", "Mz"], "transMatrix": [[0, -0.707107, -0.707107], [0, -0.707107, 0.707107], [-1, -0, 0]]},
			{"name": 4005, "type": "DispBeamColumn3d", "nodes": [4004, 4005], "sections": ["4001", "4001", "4001", "4001", "4001"], "integration": {"type": "Legendre"}, "massperlength": 0, "crdTransformation": "2"},
			{"name": 4006, "type": "ZeroLength", "nodes": [4005, 4006], "materials": ["4003", "4003", "4003", "4003", "4002", "4002"], "dof": ["P", "Vy", "Vz", "T", "My", "Mz"], "transMatrix": [[0, -0.707107, -0.707107], [0, -0.707107, 0.707107], [-1, -0, 0]]},
			{"name": 4007, "type": "ElasticBeam3d", "nodes": [4006, 4007], "E": 8e+07, "G": 0.002, "A": 2e+08, "Jx": 1e+08, "Iy": 1e+08, "Iz": 1e+08, "massperlength": 0, "releasez": 0, "releasey": 0, "crdTransformation": "2"},
			{"name": 4008, "type": "ZeroLength", "nodes": [4007, 4008], "materials": ["4015", "4003", "4003", "4003", "4003", "4003"], "dof": ["P", "Vy", "Vz", "T", "My", "Mz"], "transMatrix": [[0, -0.707107, -0.707107], [0, -0.707107, 0.707107], [-1, -0, 0]]},
			{"name": 4009, "type": "ElasticBeam3d", "nodes": [4008, 3002], "E": 8e+07, "G": 0.002, "A": 2e+08, "Jx": 1e+08, "Iy": 1e+08, "Iz": 1e+08, "massperlength": 0, "releasez": 0, "releasey": 0, "crdTransformation": "2"},
			{"name": 111220, "type": "ElasticBeam3d", "nodes": [1008, 3001], "E": 1.25536e+07, "G": 0.1, "A": 2.93e+07, "Jx": 1e+06, "Iy": 1e+06, "Iz": 1e+06, "massperlength": 0, "releasez": 0, "releasey": 0, "crdTransformation": "1"}
		]
	}
}
}
